holodex_cli/__init__.py
holodex_cli/__main__.py
holodex_cli/cli.py
holodex_cli/net/__init__.py
holodex_cli/net/apikey.py
holodex_cli/ui/__init__.py
holodex_cli/ui/styles.css
holodex_cli/util/__init__.py
holodex_cli/util/time.py
holodex_cli-0.1.5.dist-info/entry_points.txt
holodex_cli-0.1.5.dist-info/METADATA
holodex_cli-0.1.5.dist-info/WHEEL
holodex_cli-0.1.5.dist-info/RECORD
